praisonai/__init__.py
praisonai/__main__.py
praisonai/agent_scheduler.py
praisonai/agents_generator.py
praisonai/auto.py
praisonai/chainlit_ui.py
praisonai/deploy.py
praisonai/profiler.py
praisonai/scheduler.py
praisonai/setup.py
praisonai/test.py
praisonai/tool_resolver.py
praisonai/train.py
praisonai/train_vision.py
praisonai/upload_vision.py
praisonai/version.py
praisonai/_dev/__init__.py
praisonai/_dev/api_md.py
praisonai/acp/__init__.py
praisonai/acp/config.py
praisonai/acp/safe_edit.py
praisonai/acp/server.py
praisonai/acp/session.py
praisonai/adapters/__init__.py
praisonai/adapters/readers.py
praisonai/adapters/rerankers.py
praisonai/adapters/retrievers.py
praisonai/adapters/vector_stores.py
praisonai/api/call.py
praisonai/app/__init__.py
praisonai/app/agentos.py
praisonai/audit/__init__.py
praisonai/audit/agent_centric.py
praisonai/bots/__init__.py
praisonai/bots/discord.py
praisonai/bots/media.py
praisonai/bots/slack.py
praisonai/bots/telegram.py
praisonai/browser/__init__.py
praisonai/browser/agent.py
praisonai/browser/benchmark.py
praisonai/browser/cdp_agent.py
praisonai/browser/cdp_utils.py
praisonai/browser/cli.py
praisonai/browser/diagnostics.py
praisonai/browser/launcher.py
praisonai/browser/playwright_agent.py
praisonai/browser/profiling.py
praisonai/browser/protocol.py
praisonai/browser/report.py
praisonai/browser/server.py
praisonai/browser/sessions.py
praisonai/browser/video.py
praisonai/capabilities/__init__.py
praisonai/capabilities/a2a.py
praisonai/capabilities/assistants.py
praisonai/capabilities/audio.py
praisonai/capabilities/batches.py
praisonai/capabilities/completions.py
praisonai/capabilities/container_files.py
praisonai/capabilities/containers.py
praisonai/capabilities/embeddings.py
praisonai/capabilities/files.py
praisonai/capabilities/fine_tuning.py
praisonai/capabilities/guardrails.py
praisonai/capabilities/images.py
praisonai/capabilities/mcp.py
praisonai/capabilities/messages.py
praisonai/capabilities/moderations.py
praisonai-4.2.4.dist-info/METADATA
praisonai-4.2.4.dist-info/WHEEL
praisonai-4.2.4.dist-info/entry_points.txt
praisonai-4.2.4.dist-info/top_level.txt
praisonai-4.2.4.dist-info/RECORD
